[{"source":"User is on Browser","steps":[{"name":"User is on Browser","aggregatedDurations":{"median":5.7943708,"average":5.7943708}}]},{"source":"User enters URL in address bar","steps":[{"name":"User enters URL in address bar","aggregatedDurations":{"median":4.0570403,"average":4.0570403}}]},{"source":"User lands on Universal class Home Page","steps":[{"name":"User lands on Universal class Home Page","aggregatedDurations":{"median":0.2455027,"average":0.2455027}}]},{"source":"User is on Universal Class Page","steps":[{"name":"User is on Universal Class Page","aggregatedDurations":{"median":5.3146936,"average":5.361015288888888}}]},{"source":"User clicks on more option button","steps":[{"name":"User clicks on more option button","aggregatedDurations":{"median":0.079236,"average":0.0814871388888889}}]},{"source":"User is able to view options like Sign in, subscribe , etc","steps":[{"name":"User is able to view options like Sign in, subscribe , etc","aggregatedDurations":{"median":0.2430982,"average":0.2430982}}]},{"source":"User click on close button to close the more option list","steps":[{"name":"User click on close button to close the more option list","aggregatedDurations":{"median":0.2515265,"average":0.2515265}}]},{"source":"User click on Sign in button and Member sign in window will appears","steps":[{"name":"User click on Sign in button and Member sign in window will appears","aggregatedDurations":{"median":1.7158311,"average":1.7158311}}]},{"source":"User click on Sign in button and see two text box for email and password resp","steps":[{"name":"User click on Sign in button and see two text box for email and password resp","aggregatedDurations":{"median":2.5486487,"average":2.5486487}}]},{"source":"User click on Sign in button and Enter new email for sign up","steps":[{"name":"User click on Sign in button and Enter new email for sign up","aggregatedDurations":{"median":6.7018666,"average":6.7018666}}]},{"source":"User click on Sign in button and Enter email and password for login","steps":[{"name":"User click on Sign in button and Enter email and password for login","aggregatedDurations":{"median":6.0792567,"average":6.0792567}}]},{"source":"User click on Sign in button and Enter credentials and face a double check.","steps":[{"name":"User click on Sign in button and Enter credentials and face a double check.","aggregatedDurations":{"median":7.9236904,"average":7.9236904}}]},{"source":"User click on Sign in button and Enter credentials and get a tip for wrong password.","steps":[{"name":"User click on Sign in button and Enter credentials and get a tip for wrong password.","aggregatedDurations":{"median":5.4707082,"average":5.4707082}}]},{"source":"User click on Sign in button and Enter credentials to land on home page","steps":[{"name":"User click on Sign in button and Enter credentials to land on home page","aggregatedDurations":{"median":5.9715927,"average":5.9715927}}]},{"source":"User click on forgot password link","steps":[{"name":"User click on forgot password link","aggregatedDurations":{"median":5.2279008,"average":5.2279008}}]},{"source":"User click on email textbox for recovery","steps":[{"name":"User click on email textbox for recovery","aggregatedDurations":{"median":1.6525805,"average":1.6525805}}]},{"source":"User click on Search bar and enter text","steps":[{"name":"User click on Search bar and enter text","aggregatedDurations":{"median":0.2907923,"average":0.2907923}}]},{"source":"User click on Search bar and enter matched data","steps":[{"name":"User click on Search bar and enter matched data","aggregatedDurations":{"median":1.7564278,"average":1.7564278}}]},{"source":"User click on Search bar and enter unmatched data","steps":[{"name":"User click on Search bar and enter unmatched data","aggregatedDurations":{"median":1.7773099,"average":1.7773099}}]},{"source":"User click on Search bar","steps":[{"name":"User click on Search bar","aggregatedDurations":{"median":0.2780291,"average":0.2780291}}]},{"source":"User click on Search bar and enter no text","steps":[{"name":"User click on Search bar and enter no text","aggregatedDurations":{"median":3.4979954,"average":3.4979954}}]},{"source":"User click on course catalog button","steps":[{"name":"User click on course catalog button","aggregatedDurations":{"median":0.2482125,"average":0.2482125}}]},{"source":"User click on my class button","steps":[{"name":"User click on my class button","aggregatedDurations":{"median":2.7772244,"average":2.7772244}}]}]